{"cameraMode":{"drawMode":0,"name":"Shaded","section":"Shading Mode"},"sceneLighting":true,"audioPlay":false,"sceneViewState":{"m_AlwaysRefresh":false,"showFog":true,"showSkybox":true,"showFlares":true,"showImageEffects":true,"showParticleSystems":true,"showVisualEffectGraphs":true,"m_FxEnabled":true},"in2DMode":false,"pivot":{"x":2.8485941886901857,"y":4.391517162322998,"z":-0.21860787272453309},"rotation":{"x":-0.17508596181869508,"y":0.6569633483886719,"z":-0.16076858341693879,"w":-0.715465247631073},"size":0.576208770275116,"orthographic":false}